{
  "default_parts": [
    {
      "name": "Outfit",
      "id": 0
    },
    {
      "name": "Face",
      "ids": [ 2, 3 ]
    }
  ],
  "characters": [
    {
      "id": "ama",
      "name": "Amane Suou"
    },
    {
      "id": "amm",
      "name": "Amane Suou",
      "label": "Middle School Glasses"
    },
    {
      "id": "amp",
      "name": "Amane Suou",
      "label": "Middle School"
    },
    {
      "id": "mak",
      "name": "Makina Irisu",
      "game_parts": [
        {
          "game_ids": [ "idolmahou", "idolmahou1", "idolmahou2" ],
          "parts": [
            {
              "name": "Outfit",
              "id": 0
            },
            {
              "name": "Face",
              "ids": [ 2, 3 ]
            },
            {
              "name": "Sunglasses",
              "id": 4,
              "enabled": false
            }
          ]
        }
      ]
    },
    {
      "id": "mic",
      "name": "Michiru Matsushima",
      "parts": [
        {
          "name": "Outfit",
          "id": 0
        },
        {
          "name": "Face",
          "ids": [ 2, 3 ]
        },
        {
          "name": "Nyan Body",
          "id": 4,
          "enabled": false
        },
        {
          "name": "Nyan Face",
          "id": 5,
          "enabled": false
        },
        {
          "name": "Effect",
          "id": 6,
          "enabled": false
        }
      ],
      "game_parts": [
        {
          "game_ids": [ "yuukan" ],
          "parts": [
            {
              "name": "Outfit",
              "id": 0
            },
            {
              "name": "Face",
              "ids": [ 2, 3 ]
            },
            {
              "name": "Effect 1",
              "id": 5,
              "enabled": false
            },
            {
              "name": "Effect 2",
              "id": 6,
              "enabled": false
            },
            {
              // Behold! One sprite Id for a chin! What's the point?
              "name": "Chin",
              "id": 4
            }
          ]
        },
        {
          "game_ids": [ "idolmahou", "idolmahou1", "idolmahou2" ],
          "parts": [
            {
              "name": "Outfit",
              "id": 0
            },
            {
              "name": "Face",
              "ids": [ 2, 3 ]
            },
            {
              "name": "Nyan Body",
              "id": 5,
              "enabled": false
            },
            {
              "name": "Nyan Face",
              "id": 6,
              "enabled": false
            },
            {
              "name": "Effect",
              "id": 7,
              "enabled": false
            },
            {
              "name": "Wand",
              "id": 8,
              "enabled": false
            },
            {
              // Behold! One sprite Id for a chin! What's the point?
              "name": "Chin",
              "id": 4
            }
          ]
        }
      ]
    },
    {
      "id": "mib",
      "name": "Michiru Matsushima",
      "label": "Black Hair",
      "parts": [
        {
          "name": "Outfit",
          "id": 0
        },
        {
          "name": "Face",
          "ids": [ 2, 3 ]
        },
        {
          "name": "Effect",
          "id": 6,
          "enabled": false
        }
      ]
    },
    {
      "id": "micfly",
      "name": "Michiru Matsushima",
      "label": "Flying",
      "parts": [
        {
          "name": "Outfit",
          "id": 0
        },
        {
          "name": "Face",
          "id": 1
        }
      ],
      "game_parts": [
        {
          "game_ids": [ "idolmahou", "idolmahou2" ],
          "parts": [
            {
              "name": "Outfit",
              "id": 0
            },
            {
              "name": "Face",
              "id": 1
            },
            {
              "name": "Nyan",
              "id": 2,
              "enabled": false
            }
          ]
        }
      ]
    },
    {
      "id": "mickv",
      "name": "Michiru Matsushima",
      "label": "Transform",
      "parts": [
        {
          "name": "Outfit",
          "id": 0
        },
        {
          "name": "Magic",
          "id": 1
        }
      ]
    },
    {
      "id": "sac",
      "name": "Sachi Komine"
    },
    {
      "id": "sas",
      "name": "Sachi Komine",
      "label": "Battle",
      "game_parts": [
        {
          "game_ids": [ "rakuen", "idolmahou", "idolmahou1", "idolmahou2" ],
          "parts": [
            {
              "name": "Outfit",
              "id": 0
            },
            {
              "name": "Face",
              "id": 1
            }
          ]
        }
      ]
      // Outfit 8, Labyrinth, no face
    },
    {
      "id": "yum",
      "name": "Yumiko Sakaki",
      "game_parts": [
        {
          "game_ids": [ "idolmahou", "idolmahou1", "idolmahou2" ],
          "parts": [
            {
              "name": "Outfit",
              "id": 0
            },
            {
              "name": "Face",
              "ids": [ 2, 3 ]
            },
            {
              "name": "Dazs",
              "id": 4,
              "enabled": false
            }
          ]
        }
      ]
    },
    {
      "id": "yummoz",
      "name": "Yumiko Sakaki",
      "label": "Mosiac",
      "parts": [
        {
          "name": "Frame",
          "id": 0
        }
      ]
    },
    {
      "ids": [ "kar", "kap" ],
      "name": "Kazuki Kazami"
    },
    {
      "id": "kaz",
      "name": "Kazuki Kazami",
      "label": "Magical Girl",
      "game_parts": [
        {
          "game_ids": [ "idolmahou", "idolmahou1", "idolmahou2" ],
          "parts": [
            {
              "name": "Outfit",
              "id": 0
            },
            {
              "name": "Face",
              "ids": [ 2, 3 ]
            },
            {
              "name": "Than Body",
              "id": 5,
              "enabled": false
            },
            {
              "name": "Than Mouth",
              "id": 6,
              "enabled": false
            }
          ]
        }
      ]
    },
    {
      "id": "kazfly",
      "name": "Kazuki Kazami",
      "label": "Flying",
      "parts": [
        {
          "name": "Outfit",
          "id": 0
        },
        {
          "name": "Than",
          "id": 1
        }
      ]
    },
    {
      "id": "kapkv",
      "name": "Kazuki Kazami",
      "label": "Transform",
      "parts": [
        {
          "name": "Outfit",
          "id": 0
        },
        {
          "name": "Than",
          "id": 1
        }
      ]
    },
    {
      "id": "chi",
      "name": "Chizuru Tachibana",
      "game_parts": [
        {
          "game_ids": [ "idolmahou", "idolmahou1", "idolmahou2" ],
          "parts": [
            {
              "name": "Outfit",
              "id": 0
            },
            {
              "name": "Face",
              "ids": [ 2, 3 ]
            },
            {
              "name": "Microphone",
              "id": 5,
              "enabled": false
            }
          ]
        }
      ]
    },
    {
      "id": "jb",
      "name": "JB",
      "game_parts": [
        {
          "game_ids": [ "idolmahou", "idolmahou1" ],
          "parts": [
            {
              "name": "Outfit",
              "id": 0
            },
            {
              "name": "Face",
              "ids": [ 2, 3 ]
            },
            {
              "name": "Sunglasses",
              "id": 4,
              "enabled": false
            },
            {
              "name": "Hat",
              "id": 5,
              "enabled": false
            }
          ]
        }
      ]
    },
    {
      "id": "jbs",
      "name": "JB",
      "label": "Past"
    },
    {
      "id": "asa",
      "name": "Asako Kusakabe"
    },
    {
      "id": "kia",
      "name": "Chiara Farrell"
    },
    {
      "id": "yuj",
      "name": "Yuuji Kazami",
      "type": "main",
      "label": "Child"
    },
    {
      "ids": [ "osr", "osl" ],
      "name": "Heath Oslo"
    },

    // RELATIVES & FRIENDS
    {
      "id": "saf",
      "name": "Sachi's Father"
    },
    {
      "id": "sam",
      "name": "Sachi's Mother"
    },
    {
      "id": "yuf",
      "name": "Michiaki Sakaki",
      "title": "Yumiko's Father"
    },
    {
      "id": "mif",
      "name": "Michiru's Friend",
      "game_parts": [
        {
          "game_ids": [ "idolmahou", "idolmahou1", "idolmahou2" ],
          "parts": [
            {
              "name": "Outfit",
              "id": 0
            },
            {
              "name": "Face",
              "ids": [ 2, 3 ]
            },
            {
              "name": "Blush",
              "id": 1,
              "enabled": false
            }
          ]
        }
      ]
    },
    {
      "id": "kiy",
      "name": "Kiyoka Irisu",
      "title": "Makina's Mother"
    },
    {
      "id": "yjf",
      "name": "Ryouji Kazami",
      "title": "Yuuji's Father"
    },
    {
      "id": "yjm",
      "name": "Satoko Kazami",
      "title": "Yuuji's Mother"
    },

    // MILITARY
    {
      "id": "dan",
      "name": "Daniel Bone"
    },
    {
      "id": "edi",
      "name": "Edward Walker"
    },
    {
      "id": "gar",
      "name": "Agnes Garrett"
    },
    {
      "id": "jei",
      "name": "Justin Mikemeyer"
    },
    {
      "id": "mir",
      "name": "Milliela Stanfield",
      "parts": [
        {
          "name": "Outfit",
          "id": 0
        },
        {
          "name": "Face",
          "ids": [ 2, 3 ]
        },
        {
          "name": "Effect",
          "id": 6,
          "enabled": false
        }
      ],
      "game_parts": [
        {
          "game_ids": [ "rakuen" ],
          "parts": [
            {
              "name": "Outfit",
              "id": 0
            },
            {
              "name": "Face",
              "ids": [ 2, 3 ]
            },
            {
              "name": "Helmet",
              "id": 4,
              "enabled": false
            },
            {
              "name": "Effect",
              "id": 6,
              "enabled": false
            }
          ]
        }
      ]
    },
    {
      "id": "rob",
      "name": "Robert Wallson"
    },

    // AMANE ROUTE
    {
      "id": "hir",
      "name": "Hiroka Tamaki",
      "label": "Amane's Classmate"
    },
    {
      "id": "ibu",
      "name": "Haruna Ibuki",
      "label": "Amane's Classmate"
    },
    {
      "id": "kan",
      "name": "Saaya Kaneda",
      "label": "Amane's Classmate"
    },
    {
      "id": "koi",
      "name": "Ritsu Koide",
      "label": "Amane's Classmate"
    },
    {
      "id": "kom",
      "name": "Megumi Komori",
      "label": "Amane's Classmate"
    },
    {
      "id": "och",
      "name": "Yoshihiko Ochi",
      "label": "Amane's Teacher"
    },
    {
      "id": "sak",
      "name": "Chiaki Sakashita",
      "label": "Amane's Classmate"
    },
    {
      "id": "skm",
      "name": "Minori Sakuma",
      "label": "Amane's Classmate"
    },
    {
      "id": "skr",
      "name": "Mifuyu Sakurai",
      "label": "Amane's Classmate"
    },
    {
      "id": "tas",
      "name": "Keiji Sakashita"
    },

    // OTHER
    {
      "ids": [ "dav", "dave" ],
      "name": "Professor Dave"
    },
    {
      "id": "meg",
      "name": "Goddess"
    },
    {
      "id": "str",
      "name": "Stranger"
    },
    {
      "id": "kam",
      "name": "Kami-sama"
      // Surprisingly uses normal part setup
    },
    {
      // Unused
      "id": "nan",
      "name": "Nanano Suou"
    },
    {
      // Unused
      "id": "ren",
      "name": "Renge Yamabuki"
    },

    // INHUMAN
    {
      "id": "cha",
      "name": "Chaos",
      "parts": [
        {
          "name": "Body",
          "id": 0
        }
      ]
    },
    {
      "id": "gho",
      "name": "Ghost",
      "parts": [
        {
          "name": "Body",
          "id": 0
        }
      ]
    },
    {
      "id": "joh",
      "name": "John",
      "title": "Yuuji's Dog",
      "parts": [
        {
          "name": "Body",
          "id": 0
        },
        {
          "name": "Nothing",
          "id": 2,
          "enabled": false
        }
      ]
    },
    {
      "id": "mar",
      "name": "Marin",
      "parts": [
        {
          "name": "Body",
          "id": 0
        }
      ]
    },
    {
      "id": "nya",
      "name": "Nyanmel",
      "parts": [
        {
          "name": "Body",
          "id": 0
        },
        {
          "name": "Face",
          "id": 2
        }
      ],
      "game_parts": [
        {
          "game_ids": [ "idolmahou", "idolmahou1", "idolmahou2" ],
          "parts": [
            {
              "name": "Body",
              "id": 2
            },
            {
              "name": "Face",
              "ids": [ 3, 4 ]
            },
            {
              "name": "Bubble",
              "id": 0
            },
            {
              "name": "Effect",
              "id": 1,
              "enabled": false
            }
          ]
        }
      ]
    },
    {
      "id": "tan",
      "name": "Thanatochu",
      "parts": [
        {
          "name": "Body",
          "id": 2
        },
        {
          "name": "Face",
          "id": 3
        },
        {
          "name": "Bubble",
          "id": 0
        }
      ]
    },
    {
      "id": "mag",
      "name": "Tunafish Man",
      "parts": [
        {
          "name": "Body",
          "id": 0
        },
        {
          "name": "Unknown",
          "id": 2
        }
      ]
    },
    {
      "id": "iza",
      "name": "Isabella Fitzgerald",
      "title": "Major Isabella Fitzgerald",
      "parts": [
        {
          "name": "Outfit",
          "id": 0
        },
        {
          "name": "Face",
          "ids": [ 2, 3 ]
        },
        {
          "name": "Blush",
          "id": 1,
          "enabled": false
        }
      ]
    },
    {
      "id": "mro",
      "name": "Marion Garland",
      "parts": [
        {
          "name": "Outfit",
          "id": 0
        },
        {
          "name": "Face",
          "ids": [ 2, 3 ]
        },
        {
          "name": "Blush",
          "id": 1,
          "enabled": false
        }
      ]
    },
    {
      "id": "nob",
      "name": "Ramon Noboa",
      "parts": [
        {
          "name": "Outfit",
          "id": 0
        },
        {
          "name": "Face",
          "ids": [ 2, 3 ]
        },
        {
          "name": "Sunglasses",
          "id": 4,
          "enabled": false
        }
      ]
    },
    {
      "id": "adm",
      "name": "Adam Black"
    },
    {
      "id": "rby",
      "name": "Zoey Graham",
      "title": "Robbie's Wife"
    },
    {
      "id": "tpo",
      "name": "Typhoon"
    },
    {
      "id": "tra",
      "name": "Travis"
    },
    {
      "id": "yam",
      "name": "Yamamoto"
    }
  ]
}
